MobileVisionTest/__init__.py
MobileVisionTest/api/MobileVisionAPI.py
MobileVisionTest/api/__init__.py
MobileVisionTest/core/__init__.py
MobileVisionTest/core/check.py
MobileVisionTest/core/image_utils.py
MobileVisionTest/core/model_trainer.py
MobileVisionTest/core/ocr_engine.py
MobileVisionTest/core/ui_detector.py
MobileVisionTest/core/vie_correct.py
MobileVisionTest/integration/__init__.py
MobileVisionTest/integration/device_bridge.py
MobileVisionTest/yolo/yolo_train/__init__.py
MobileVisionTest/yolo/yolo_train/train_yolo.py
mobilevisiontest-1.0.1.dist-info/METADATA
mobilevisiontest-1.0.1.dist-info/WHEEL
mobilevisiontest-1.0.1.dist-info/top_level.txt
mobilevisiontest-1.0.1.dist-info/RECORD
