Metadata-Version: 2.4
Name: MobileVisionTest
Version: 1.0.1
Summary: A library for automated mobile testing using OCR and AI-based UI recognition
Author: Dieuanh
Author-email: Dieuanh <dieuanht29@gmail.com>
Classifier: Programming Language :: Python :: 3
Classifier: License :: OSI Approved :: MIT License
Classifier: Operating System :: OS Independent
Requires-Python: >=3.8
Requires-Dist: huggingface-hub==0.24.7
Requires-Dist: tokenizers==0.20.3
Requires-Dist: transformers==4.46.0
Dynamic: author
Dynamic: requires-python
